LICENSE
MANIFEST.in
README.rst
setup.py
django_sendmail_form.egg-info/PKG-INFO
django_sendmail_form.egg-info/SOURCES.txt
django_sendmail_form.egg-info/dependency_links.txt
django_sendmail_form.egg-info/top_level.txt
sendmail_form/__init__.py
sendmail_form/forms.py
sendmail_form/settings.py
sendmail_form/utils.py
sendmail_form/locale/ru/LC_MESSAGES/django.mo
sendmail_form/locale/ru/LC_MESSAGES/django.po